{
    "type": "enum",
    "title": {
        "en": "Operation Mode",
        "nl": "Bedrijfsmodus"
    },
    "getable": true,
    "setable": true,
  	"uiComponent": "picker",
    "values": [{
        "id": "off",
        "title": {
            "en": "Off",
            "nl": "Uit"
        }
    }, {
        "id": "cool",
        "title": {
            "en": "Cooling",
            "nl": "Koelen"
        }
    }, {
        "id": "heat",
        "title": {
            "en": "Heating",
            "nl": "Verwarmen"
        }
    }, {
        "id": "auto",
        "title": {
            "en": "Auto",
            "nl": "Auto"
        }
    }, {
        "id": "fan",
        "title": {
            "en": "Fan",
            "nl": "Ventilator"
        }
    }, {
        "id": "dehumid",
        "title": {
            "en": "Dry",
            "nl": "Drogen"
        }
    }]
}
